ringity/__init__.py
ringity/_version.py
ringity/_data/HM_ADIPOGENESIS.csv
ringity/_data/HM_ALLOGRAFT_REJECTION.csv
ringity/_data/HM_ANDROGEN_RESPONSE.csv
ringity/_data/HM_ANGIOGENESIS.csv
ringity/_data/HM_APICAL_JUNCTION.csv
ringity/_data/HM_APICAL_SURFACE.csv
ringity/_data/HM_APOPTOSIS.csv
ringity/_data/HM_BILE_ACID_METABOLISM.csv
ringity/_data/HM_CHOLESTEROL_HOMEOSTASIS.csv
ringity/_data/HM_COAGULATION.csv
ringity/_data/HM_COMPLEMENT.csv
ringity/_data/HM_DNA_REPAIR.csv
ringity/_data/HM_E2F_TARGETS.csv
ringity/_data/HM_EPITHELIAL_MESENCHYMAL_TRANSITION.csv
ringity/_data/HM_ESTROGEN_RESPONSE_EARLY.csv
ringity/_data/HM_ESTROGEN_RESPONSE_LATE.csv
ringity/_data/HM_FATTY_ACID_METABOLISM.csv
ringity/_data/HM_G2-M_CHECKPOINT.csv
ringity/_data/HM_GLYCOLYSIS.csv
ringity/_data/HM_HEDGEHOG_SIGNALING.csv
ringity/_data/HM_HEME_METABOLISM.csv
ringity/_data/HM_HYPOXIA.csv
ringity/_data/HM_IL-2STAT5_SIGNALING.csv
ringity/_data/HM_IL-6JAKSTAT3_SIGNALING.csv
ringity/_data/HM_INFLAMMATORY_RESPONSE.csv
ringity/_data/HM_INTERFERON_ALPHA_RESPONSE.csv
ringity/_data/HM_INTERFERON_GAMMA_RESPONSE.csv
ringity/_data/HM_KRAS_SIGNALING_DN.csv
ringity/_data/HM_KRAS_SIGNALING_UP.csv
ringity/_data/HM_MITOTIC_SPINDLE.csv
ringity/_data/HM_MTORC1_SIGNALING.csv
ringity/_data/HM_MYC_TARGETS_V1.csv
ringity/_data/HM_MYC_TARGETS_V2.csv
ringity/_data/HM_MYOGENESIS.csv
ringity/_data/HM_NOTCH_SIGNALING.csv
ringity/_data/HM_OXIDATIVE_PHOSPHORYLATION.csv
ringity/_data/HM_P53_PATHWAY.csv
ringity/_data/HM_PANCREAS_BETA_CELLS.csv
ringity/_data/HM_PI3KAKTMTOR_SIGNALING.csv
ringity/_data/HM_PPEROXISOME.csv
ringity/_data/HM_PROTEIN_SECRETION.csv
ringity/_data/HM_REACTIVE_OXYGEN_SPECIES_PATHWAY.csv
ringity/_data/HM_SPERMATOGENESIS.csv
ringity/_data/HM_TGF-BETA_SIGNALING.csv
ringity/_data/HM_TNF-ALPHA_SIGNALING_VIA_NF-KB.csv
ringity/_data/HM_UNFOLDED_PROTEIN_RESPONSE.csv
ringity/_data/HM_UV_RESPONSE_DN.csv
ringity/_data/HM_UV_RESPONSE_UP.csv
ringity/_data/HM_WNT-BETA_CATENIN_SIGNALING.csv
ringity-0.4a4.dist-info/licenses/LICENSE.txt
ringity-0.4a4.dist-info/METADATA
ringity-0.4a4.dist-info/WHEEL
ringity-0.4a4.dist-info/top_level.txt
ringity-0.4a4.dist-info/RECORD
